st_kaggle_connector/__init__.py
st_kaggle_connector/kaggle_connector.py
st_kaggle_connector-0.1.3.dist-info/METADATA
st_kaggle_connector-0.1.3.dist-info/WHEEL
st_kaggle_connector-0.1.3.dist-info/top_level.txt
st_kaggle_connector-0.1.3.dist-info/RECORD
