Metadata-Version: 2.1
Name: st-kaggle-connector
Version: 0.1.3
Summary: Kaggle dataset connector for Streamlit
Home-page: https://github.com/arsentievalex/kaggle-streamlit-data-connector/tree/main
Author: Oleksandr Arsentiev
Author-email: <arsentiev9393@gmail.com>
License: MIT
Keywords: streamlit,custom,component,kaggle,dataset,connector
Requires-Dist: streamlit
Requires-Dist: pandas
Requires-Dist: kaggle
